nntp/__init__.py
nntp/fifo.py
nntp/headerdict.py
nntp/nntp.py
nntp/types.py
nntp/utils.py
nntp/yenc.py
pynntp-2.0.1.dist-info/LICENSE
pynntp-2.0.1.dist-info/METADATA
pynntp-2.0.1.dist-info/WHEEL
pynntp-2.0.1.dist-info/RECORD
