Metadata-Version: 2.1
Name: pynntp
Version: 2.0.1
Summary: NNTP Library (including compressed headers)
License: GPL-3.0-or-later
Author: Byron Platt
Author-email: byron.platt@gmail.com
Requires-Python: >=3.9
Classifier: License :: OSI Approved :: GNU General Public License v3 (GPLv3)
Classifier: License :: OSI Approved :: GNU General Public License v3 or later (GPLv3+)
Classifier: Operating System :: OS Independent
Classifier: Programming Language :: Python :: 3
Classifier: Programming Language :: Python :: 3.9
Classifier: Programming Language :: Python :: 3.10
Classifier: Programming Language :: Python :: 3.11
Classifier: Programming Language :: Python :: 3.12
Classifier: Topic :: Communications :: Usenet News
